rf_runner/__init__.py
rf_runner/api.py
rf_runner/arg_parser.py
rf_runner/config.py
rf_runner/exceptions.py
rf_runner/executor.py
rf_runner/fetcher.py
rf_runner/fetcher_factory.py
rf_runner/publisher.py
rf_runner/publisher_factory.py
rf_runner/runner.py
rf_service-0.3.2.data/scripts/rf-service
rf_service-0.3.2.dist-info/LICENSE
rf_service-0.3.2.dist-info/METADATA
rf_service-0.3.2.dist-info/WHEEL
rf_service-0.3.2.dist-info/top_level.txt
rf_service-0.3.2.dist-info/RECORD
