Metadata-Version: 2.1
Name: rf-service
Version: 0.3.2
Summary: Robot Framework service
Home-page: https://github.com/devopsspiral/rf-service
Author: Michał Wcisło
Author-email: mwcislo999@gmail.com
License: MIT
Keywords: robotframework testing test automation
Platform: UNKNOWN
Classifier: Development Status :: 2 - Pre-Alpha
Classifier: Programming Language :: Python :: 3
Classifier: License :: OSI Approved :: MIT License
Classifier: Operating System :: OS Independent
Classifier: Topic :: Software Development :: Testing
Requires-Python: >=3.6
Requires-Dist: robotframework
Requires-Dist: datetime
Requires-Dist: requests
Requires-Dist: flask
Requires-Dist: flask-cors
Requires-Dist: gevent
Requires-Dist: azure-storage-blob
